setup.py
traceall/__init__.py
traceall.egg-info/PKG-INFO
traceall.egg-info/SOURCES.txt
traceall.egg-info/dependency_links.txt
traceall.egg-info/pbr.json
traceall.egg-info/top_level.txt