Metadata-Version: 1.0
Name: traceall
Version: 0.1.0
Summary: Development utility: under development
Home-page: https://github.com/srafehi/traceall
Author: Shady Rafehi
Author-email: UNKNOWN
License: MIT
Keywords: stack,systrace,trace
Platform: UNKNOWN
